qwazzock/__init__.py
qwazzock/game.py
qwazzock/logs.py
qwazzock/server.py
qwazzock/static/audio/meh.mp3
qwazzock/static/css/common.css
qwazzock/static/dialog-polyfill/dialog-polyfill.css
qwazzock/static/dialog-polyfill/dialog-polyfill.esm.js
qwazzock/static/dialog-polyfill/dialog-polyfill.js
qwazzock/static/icons/favicon.ico
qwazzock/static/images/buzzer.svg
qwazzock/static/js/host_client.js
qwazzock/static/js/player_client.js
qwazzock/templates/base.html
qwazzock/templates/host_client.html
qwazzock/templates/player_client.html
qwazzock-0.12.0.dist-info/entry_points.txt
qwazzock-0.12.0.dist-info/WHEEL
qwazzock-0.12.0.dist-info/METADATA
qwazzock-0.12.0.dist-info/RECORD
