Metadata-Version: 2.1
Name: qwazzock
Version: 0.12.0
Summary: An app for hosting interactive quizzes.
Author: Dave Randall
Author-email: 19395688+daveygit2050@users.noreply.github.com
Requires-Python: >=3.8,<4.0
Classifier: Programming Language :: Python :: 3
Classifier: Programming Language :: Python :: 3.8
Requires-Dist: eventlet (>=0.25.2,<0.26.0)
Requires-Dist: flask (>=1.1.2,<2.0.0)
Requires-Dist: flask-socketio (>=4.2.1,<5.0.0)
Requires-Dist: pyopenssl (>=19.1.0,<20.0.0)
